hic_io.cpython-313-darwin.so
hic_io/python_binding.cpp
hic_io/reading/hic_slice.h
hic_io/reading/straw.cpp
hic_io/reading/straw.h
hic_io-1.0.16.data/data/hic_io/hic_slice.h
hic_io-1.0.16.data/data/hic_io/python_binding.cpp
hic_io-1.0.16.data/data/hic_io/straw.cpp
hic_io-1.0.16.data/data/hic_io/straw.h
hic_io-1.0.16.dist-info/licenses/LICENSE
hic_io-1.0.16.dist-info/METADATA
hic_io-1.0.16.dist-info/WHEEL
hic_io-1.0.16.dist-info/top_level.txt
hic_io-1.0.16.dist-info/RECORD
