Metadata-Version: 2.4
Name: hic_io
Version: 1.0.16
Summary: Process HiC files
Author-email: Arthur Gouhier <ajgouhier@gmail.com>
License-Expression: MIT
Project-URL: Repository, https://github.com/ajgouhier/hic_io
Requires-Python: >=3.8
License-File: LICENSE
Requires-Dist: numpy
Requires-Dist: pybind11>=2.6.0
Dynamic: license-file
